vps_backup_utils/__init__.py
vps_backup_utils/command.py
vps_backup_utils/utils/__init__.py
vps_backup_utils/utils/paths.py
vps_backup_utils/vps_backup_utils.py
vps_backup_utils-0.0.3.dist-info/LICENSE
vps_backup_utils-0.0.3.dist-info/WHEEL
vps_backup_utils-0.0.3.dist-info/METADATA
vps_backup_utils-0.0.3.dist-info/RECORD
