Metadata-Version: 2.1
Name: vps-backup-utils
Version: 0.0.3
Summary: Backup Utilities for Linux VPS with MySQL and other data
Home-page: https://github.com/lyh543/vps_backup_utils
License: MIT
Keywords: backup,vps
Author: lyh543
Author-email: lyh543@outlook.com
Requires-Python: >=3.7,<4.0
Classifier: License :: OSI Approved :: MIT License
Classifier: Programming Language :: Python :: 3
Classifier: Programming Language :: Python :: 3.10
Classifier: Programming Language :: Python :: 3.7
Classifier: Programming Language :: Python :: 3.8
Classifier: Programming Language :: Python :: 3.9
Project-URL: Repository, https://github.com/lyh543/vps_backup_utils
